playlistzip/__init__.py
playlistzip/cli.py
playlistzip-0.1.2.dist-info/entry_points.txt
playlistzip-0.1.2.dist-info/LICENSE
playlistzip-0.1.2.dist-info/WHEEL
playlistzip-0.1.2.dist-info/METADATA
playlistzip-0.1.2.dist-info/RECORD
