Metadata-Version: 2.1
Name: playlistzip
Version: 0.1.2
Summary: Join two to four youtube playlists into viewsync links. Joining is accomplished by episode numbers, collected from video titles.
Home-page: https://gitlab.com/rossvor/playlistzip
License: GPL-3.0+
Author: Ross Vorotynskij
Author-email: ross@rvcg.net
Requires-Python: >=3.7,<4.0
Classifier: Development Status :: 4 - Beta
Classifier: Environment :: Console
Classifier: Intended Audience :: Developers
Classifier: Intended Audience :: End Users/Desktop
Classifier: License :: OSI Approved :: GNU General Public License v3 or later (GPLv3+)
Classifier: Programming Language :: Python :: 3
Classifier: Programming Language :: Python :: 3.7
Classifier: Topic :: Utilities
Requires-Dist: jsonpath-rw (>=1.4,<2.0)
Requires-Dist: pycurl (>=7.43,<8.0)
